COPYING
MANIFEST.in
README.txt
ez_setup.py
setup.cfg
setup.py
qtalchemy/PBSearchDialog.py
qtalchemy/PyQtHelpers.py
qtalchemy/PyQtModels.py
qtalchemy/__init__.py
qtalchemy/commands.py
qtalchemy/foreign_key.py
qtalchemy/input_yoke.py
qtalchemy/sqlalchemy_helper.py
qtalchemy/user_attr.py
qtalchemy.egg-info/PKG-INFO
qtalchemy.egg-info/SOURCES.txt
qtalchemy.egg-info/dependency_links.txt
qtalchemy.egg-info/requires.txt
qtalchemy.egg-info/top_level.txt
qtalchemy/dialogs/__init__.py
qtalchemy/dialogs/auth.py
qtalchemy/dialogs/auth_settings.py
qtalchemy/dialogs/multiauth.py
qtalchemy/dialogs/objectforms.py
qtalchemy/dialogs/quicklist.py
qtalchemy/ext/__init__.py
qtalchemy/ext/dataviews.py
qtalchemy/ext/reporttools.py
qtalchemy/ext/dataimport/__init__.py
qtalchemy/ext/dataimport/wizard.py
qtalchemy/tests/test_cached_get.py
qtalchemy/tests/test_entity_menu.py
qtalchemy/tests/test_event_recursion.py
qtalchemy/tests/test_events.py
qtalchemy/tests/test_message_hook.py
qtalchemy/tests/test_model.py
qtalchemy/tests/test_numeric_model.py
qtalchemy/widgets/__init__.py
qtalchemy/widgets/button_edit.py
qtalchemy/widgets/date_edit.py
qtalchemy/widgets/edit-find-6.ico
qtalchemy/widgets/key_edit.py
qtalchemy/widgets/street_address_widget.py
qtalchemy/widgets/table.py
qtalchemy/widgets/tree.py
qtalchemy/widgets/view-calendar.ico
qtalchemy/widgets/viewbase.py
qtalchemy/xplatform/__init__.py
qtalchemy/xplatform/pyresource.py
qtalchemy/xplatform/stderr.py
qtalchemy/xplatform/util.py