Metadata-Version: 1.1
Name: qtalchemy
Version: 0.8.3
Summary: QtAlchemy is a framework for developing GUI database applications using SQLAlchemy and PyQt/PySide.
Home-page: https://bitbucket.org/jbmohler/qtalchemy/
Author: Joel B. Mohler
Author-email: joel@kiwistrawberry.us
License: LGPLv2+
Platform: UNKNOWN
Classifier: Development Status :: 3 - Alpha
Classifier: Intended Audience :: Developers
Classifier: License :: OSI Approved :: GNU Lesser General Public License v2 or later (LGPLv2+)
Classifier: Programming Language :: Python :: 2
Classifier: Programming Language :: Python :: 3
Classifier: Topic :: Database :: Front-Ends
Classifier: Operating System :: OS Independent
